sktensor/__init__.py
sktensor/core.py
sktensor/cp.py
sktensor/dedicom.py
sktensor/dtensor.py
sktensor/indscal.py
sktensor/ktensor.py
sktensor/pyutils.py
sktensor/rescal.py
sktensor/setup.py
sktensor/sptensor.py
sktensor/tucker.py
sktensor/utils.py
sktensor/version.py
sktensor/tests/__init__.py
sktensor/tests/sptensor_fixture.py
sktensor/tests/sptensor_rand_fixture.py
sktensor/tests/test_base.py
sktensor/tests/test_dtensor.py
sktensor/tests/test_ktensor.py
sktensor/tests/test_pyutils.py
sktensor/tests/test_sptensor.py
sktensor/tests/test_tucker_hooi.py
sktensor/tests/test_utils.py
sktensor/tests/ttm_fixture.py
scikit_tensor_py3-0.4.1.dist-info/LICENSE
scikit_tensor_py3-0.4.1.dist-info/METADATA
scikit_tensor_py3-0.4.1.dist-info/WHEEL
scikit_tensor_py3-0.4.1.dist-info/top_level.txt
scikit_tensor_py3-0.4.1.dist-info/RECORD
