Metadata-Version: 2.1
Name: scikit-tensor-py3
Version: 0.4.1
Summary: Python module for multilinear algebra and tensor factorizations
Home-page: http://github.com/evertrol/scikit-tensor-py3
Maintainer: Evert Rol
Maintainer-email: evert.rol@gmail.com
License: GPLv3
Download-URL: http://github.com/evertrol/scikit-tensor-py3
Platform: UNKNOWN
Classifier: Development Status :: 3 - Alpha
Classifier: Intended Audience :: Developers
Classifier: Intended Audience :: Science/Research
Classifier: License :: OSI Approved :: GNU General Public License v3 (GPLv3)
Classifier: Topic :: Scientific/Engineering
Classifier: Topic :: Software Development
Classifier: Operating System :: Microsoft :: Windows
Classifier: Operating System :: POSIX
Classifier: Operating System :: Unix
Classifier: Operating System :: MacOS
Classifier: Programming Language :: Python :: 3
Classifier: Programming Language :: Python :: 3.5
Classifier: Programming Language :: Python :: 3.6
Classifier: Programming Language :: Python :: 3.7
Requires-Python: >=3.5
Requires-Dist: numpy (==1.16.*)
Requires-Dist: scipy (==1.3.*)
